neojsonrpc/__init__.py
neojsonrpc/client.py
neojsonrpc/constants.py
neojsonrpc/exceptions.py
neojsonrpc/utils.py
neojsonrpc-0.1.1.dist-info/DESCRIPTION.rst
neojsonrpc-0.1.1.dist-info/LICENSE.txt
neojsonrpc-0.1.1.dist-info/METADATA
neojsonrpc-0.1.1.dist-info/RECORD
neojsonrpc-0.1.1.dist-info/WHEEL
neojsonrpc-0.1.1.dist-info/metadata.json
neojsonrpc-0.1.1.dist-info/top_level.txt
