Metadata-Version: 2.0
Name: neojsonrpc
Version: 0.1.1
Summary: A Python JSON-RPC client for the NEO blockchain.
Home-page: https://github.com/ellmetha/neojsonrpc
Author: Morgan Aubert
Author-email: morgan.aubert@zoho.com
License: MIT
Keywords: neo blockchain json-rpc json-rpc-client api
Platform: UNKNOWN
Classifier: Development Status :: 4 - Beta
Classifier: Intended Audience :: Developers
Classifier: License :: OSI Approved :: MIT License
Classifier: Natural Language :: English
Classifier: Operating System :: OS Independent
Classifier: Programming Language :: Python
Classifier: Programming Language :: Python :: 3
Classifier: Programming Language :: Python :: 3.4
Classifier: Programming Language :: Python :: 3.5
Classifier: Programming Language :: Python :: 3.6
Requires-Dist: requests (>2.0)
